presskit/__init__.py
presskit/__main__.py
presskit/cli.py
presskit/hookspecs.py
presskit/plugins.py
presskit/press.py
presskit/reload.py
presskit/utils.py
presskit/config/__init__.py
presskit/config/loader.py
presskit/config/models.py
presskit/contrib/__init__.py
presskit/contrib/livereload/__init__.py
presskit/contrib/sources/__init__.py
presskit/contrib/sources/duckdb.py
presskit/contrib/sources/postgresql.py
presskit/core/__init__.py
presskit/core/query.py
presskit/sources/__init__.py
presskit/sources/base.py
presskit/sources/duckdb.py
presskit/sources/json.py
presskit/sources/postgresql.py
presskit/sources/registry.py
presskit/sources/sqlite.py
presskit-0.0.7.dist-info/METADATA
presskit-0.0.7.dist-info/WHEEL
presskit-0.0.7.dist-info/entry_points.txt
presskit-0.0.7.dist-info/top_level.txt
presskit-0.0.7.dist-info/RECORD
