Metadata-Version: 2.4
Name: presskit
Version: 0.0.7
Summary: Static site generator
Author-email: Asif Rahman <asiftr@gmail.com>
License-Expression: MIT
Project-URL: Homepage, https://github.com/asifr/presskit
Project-URL: Documentation, https://github.com/asifr/presskit
Project-URL: Repository, https://github.com/asifr/presskit
Keywords: static site generator,static sites,ssg
Classifier: Programming Language :: Python :: 3.11
Classifier: Operating System :: OS Independent
Classifier: Environment :: Web Environment
Classifier: Topic :: Internet :: WWW/HTTP
Requires-Python: >=3.11
Requires-Dist: importlib-metadata; python_version < "3.10"
Requires-Dist: Jinja2==3.1.6
Requires-Dist: markdown==3.8
Requires-Dist: PyYAML==6.0.2
Requires-Dist: MarkupSafe==3.0.2
Requires-Dist: pydantic==2.11.4
Requires-Dist: Pygments==2.19.1
Requires-Dist: pymdown-extensions==10.15
Requires-Dist: aiosqlite>=0.19.0
Requires-Dist: jsonpath-ng>=1.6.0
Requires-Dist: watchfiles>=0.23.0
Requires-Dist: pluggy>=1.6.0
Requires-Dist: click>=8.2.1
Provides-Extra: dev
Requires-Dist: ruff; extra == "dev"
Requires-Dist: ipykernel; extra == "dev"
Requires-Dist: pytest; extra == "dev"
Requires-Dist: pytest-cov; extra == "dev"
Requires-Dist: nbformat; extra == "dev"
Provides-Extra: postgresql
Requires-Dist: asyncpg>=0.29.0; extra == "postgresql"
Provides-Extra: duckdb
Requires-Dist: duckdb>=1.3.0; extra == "duckdb"
